bin/get_config.py
bin/init.py
bin/input_validator.py
bin/resource_validator.py
conf/config.yaml
conf/defaults.yaml
conf/resources.yaml
conf/security_checks.yaml
conf/swagger.json
pytmac-3.6.0.data/scripts/_version.py
pytmac-3.6.0.data/scripts/pytmac
pytmac-3.6.0.dist-info/LICENSE
pytmac-3.6.0.dist-info/METADATA
pytmac-3.6.0.dist-info/WHEEL
pytmac-3.6.0.dist-info/top_level.txt
pytmac-3.6.0.dist-info/RECORD
