Metadata-Version: 2.1
Name: pytmac
Version: 3.6.0
License-File: LICENSE
Requires-Dist: python-dotenv (==1.0.0)
Requires-Dist: pytest-env (==0.8.1)
Requires-Dist: pytest-dotenv (==0.5.2)
Requires-Dist: PyYAML (==6.0)
Requires-Dist: pytest-cov (==4.1.0)
Requires-Dist: inquirer (==3.1.3)
